pymammotion/__init__.py
pymammotion/const.py
pymammotion/py.typed
pymammotion/agora/__init__.py
pymammotion/agora/agora_api.py
pymammotion/agora/agora_rtc_capabilities.py
pymammotion/agora/agora_websockets.py
pymammotion/aliyun/__init__.py
pymammotion/aliyun/client.py
pymammotion/aliyun/cloud_gateway.py
pymammotion/aliyun/regions.py
pymammotion/aliyun/tmp_constant.py
pymammotion/aliyun/model/aep_response.py
pymammotion/aliyun/model/connect_response.py
pymammotion/aliyun/model/dev_by_account_response.py
pymammotion/aliyun/model/login_by_oauth_response.py
pymammotion/aliyun/model/regions_response.py
pymammotion/aliyun/model/session_by_authcode_response.py
pymammotion/aliyun/model/thing_response.py
pymammotion/aliyun/tea/core.py
pymammotion/bluetooth/__init__.py
pymammotion/bluetooth/ble.py
pymammotion/bluetooth/ble_message.py
pymammotion/bluetooth/const.py
pymammotion/bluetooth/data/__init__.py
pymammotion/bluetooth/data/convert.py
pymammotion/bluetooth/data/framectrldata.py
pymammotion/bluetooth/data/notifydata.py
pymammotion/bluetooth/model/__init__.py
pymammotion/bluetooth/model/atomic_integer.py
pymammotion/data/__init__.py
pymammotion/data/mower_state_manager.py
pymammotion/data/model/__init__.py
pymammotion/data/model/account.py
pymammotion/data/model/device.py
pymammotion/data/model/device_config.py
pymammotion/data/model/device_info.py
pymammotion/data/model/device_limits.py
pymammotion/data/model/enums.py
pymammotion/data/model/errors.py
pymammotion/data/model/events.py
pymammotion/data/model/generate_geojson.py
pymammotion/data/model/generate_route_information.py
pymammotion/data/model/hash_list.py
pymammotion/data/model/location.py
pymammotion/data/model/mowing_modes.py
pymammotion/data/model/rapid_state.py
pymammotion/data/model/raw_data.py
pymammotion/data/model/region_data.py
pymammotion/data/model/report_info.py
pymammotion/data/model/work.py
pymammotion/data/mqtt/__init__.py
pymammotion/data/mqtt/event.py
pymammotion/data/mqtt/mammotion_properties.py
pymammotion-0.5.70.dist-info/METADATA
pymammotion-0.5.70.dist-info/WHEEL
pymammotion-0.5.70.dist-info/licenses/LICENSE
pymammotion-0.5.70.dist-info/RECORD
