Metadata-Version: 2.4
Name: pymammotion
Version: 0.5.70
Author: jLynx
Author-email: Michael Arthur <michael@jumblesoft.co.nz>
License-Expression: GPL-3.0
License-File: LICENSE
Requires-Python: <4.0,>=3.12
Requires-Dist: aiohttp>=3.9.1
Requires-Dist: alibabacloud-apigateway-util<0.0.3,>=0.0.2
Requires-Dist: alibabacloud-iot-api-gateway<0.0.5,>=0.0.4
Requires-Dist: betterproto2>=0.9.1
Requires-Dist: bleak-retry-connector>=3.5.0
Requires-Dist: bleak>=0.21.0
Requires-Dist: crcmod~=1.7
Requires-Dist: cryptography>=43.0.1
Requires-Dist: mashumaro~=3.13
Requires-Dist: numpy>=1.26.0
Requires-Dist: orjson<4,>=3.9.15
Requires-Dist: paho-mqtt<3,>=2.1.0
Requires-Dist: protobuf>=4.23.1
Requires-Dist: pyjwt>=2.10.1
Requires-Dist: sdp-transform>=1.1.0
Requires-Dist: shapely>=2.1.2
Requires-Dist: websockets>=13.1
